{
	"id": "4f8d2d49-4180-4993-90e7-892cce19b27b",
	"name": "Simples Dental - Local",
	"values": [
		{
			"key": "baseUrl",
			"value": "http://localhost:8080",
			"type": "default",
			"enabled": true
		},
		{
			"key": "accessToken",
			"value": "",
			"type": "secret",
			"enabled": true
		},
		{
			"key": "userId",
			"value": "",
			"type": "default",
			"enabled": true
		}
	],
	"_postman_variable_scope": "environment",
	"_postman_exported_at": "2025-04-10T20:43:09.702Z",
	"_postman_exported_using": "Postman/11.40.2-250409-1302"
}